[
    {
        "title": "Traditional Scythian-Occupied Region East of Ukraine",
        "link": "https://www.worldhistory.org/image/11074/traditional-scythian-occupied-region-east-of-ukrai/",
        "category": "history"
    },
    {
        "title": "Kievan Rus",
        "link": "https://www.worldhistory.org/Kievan_Rus/",
        "category": "history"
    },
    {
        "title": "Saint Sophia Cathedral, Kyiv",
        "link": "https://www.worldhistory.org/Saint_Sophia_Cathedral,_Kyiv/",
        "category": "history"
    },
    {
        "title": "Khotyn Fortress",
        "link": "https://www.worldhistory.org/Khotyn_Fortress/",
        "category": "history"
    },
    {
        "title": "The History of the Ukrainian Region",
        "link": "https://www.worldhistory.org/collection/141/the-history-of-the-ukrainian-region/",
        "category": "history"
    },
    {
        "title": "Khotyn Fortress",
        "link": "https://www.worldhistory.org/image/14901/khotyn-fortress/",
        "category": "history"
    },
    {
        "title": "Holy Cross Cathedral, Uzhhorod",
        "link": "https://www.worldhistory.org/image/15213/holy-cross-cathedral-uzhhorod/",
        "category": "history"
    },
    {
        "title": "Peasant family by Taras Shevchenko",
        "link": "https://www.worldhistory.org/image/14886/peasant-family-by-taras-shevchenko/",
        "category": "history"
    },
    {
        "title": "Khotyn Stronghold from the North",
        "link": "https://www.worldhistory.org/image/14920/khotyn-stronghold-from-the-north/",
        "category": "history"
    },
    {
        "title": "Courtyard of the Khotyn Stronghold",
        "link": "https://www.worldhistory.org/image/14922/courtyard-of-the-khotyn-stronghold/",
        "category": "history"
    },
    {
        "title": "Ruins of the Bastion of the Khotyn Fortress",
        "link": "https://www.worldhistory.org/image/14921/ruins-of-the-bastion-of-the-khotyn-fortress/",
        "category": "history"
    },
    {
        "title": "Mauritius Square",
        "link": "https://www.worldhistory.org/image/7774/mauritius-square/",
        "category": "history"
    },
    {
        "title": "Potocki Mausoleum Chapel in Pechera",
        "link": "https://www.worldhistory.org/image/15173/potocki-mausoleum-chapel-in-pechera/",
        "category": "history"
    },
    {
        "title": "Interior of Saint Sophia Cathedral, Kyiv",
        "link": "https://www.worldhistory.org/image/14848/interior-of-saint-sophia-cathedral-kyiv/",
        "category": "history"
    },
    {
        "title": "Saint Sophia Cathedral, Kyiv",
        "link": "https://www.worldhistory.org/image/14795/saint-sophia-cathedral-kyiv/",
        "category": "history"
    },
    {
        "title": "Map of the Khotyn Fortress",
        "link": "https://www.worldhistory.org/image/14923/map-of-the-khotyn-fortress/",
        "category": "history"
    },
    {
        "title": "Battle of Khotyn (1621)",
        "link": "https://www.worldhistory.org/image/14924/battle-of-khotyn-1621/",
        "category": "history"
    },
    {
        "title": "Bell Tower of Saint Sophia Cathedral, Kyiv",
        "link": "https://www.worldhistory.org/image/14808/bell-tower-of-saint-sophia-cathedral-kyiv/",
        "category": "history"
    },
    {
        "title": "Fresco in the Saint Sophia Cathedral",
        "link": "https://www.worldhistory.org/image/14822/fresco-in-the-saint-sophia-cathedral/",
        "category": "history"
    },
    {
        "title": "Portrait of Ivan Mazepa",
        "link": "https://www.worldhistory.org/image/14821/portrait-of-ivan-mazepa/",
        "category": "history"
    }
]
