[
    {
        "name": "우크라 “앞으로 24시간이 결정적”…러, 병력 손실 첫 인정",
        "description": "<비비시>(BBC) 방송은 러시아 군도 이날 전투에서 일부 병력을 잃었다고 인정했지만, 구체적인 피해 상황을 거론하지 않은 채 \n우크라이나 군보다 피해...",
        "link": "https://www.hani.co.kr/arti/international/international_general/1032843.html",
        "date": "2주 전",
        "image_path": "https://flexible.img.hani.co.kr/flexible/normal/730/487/imgdb/original/2022/0228/20220228501236.jpg",
        "catagory": "교전 최신 상황"
    },
    {
        "name": "푸틴 “우크라이나 전투에 추가 징집병 안 보낸다”",
        "description": "이런 상황에서 푸틴 대통령의 공식 발언은 러시아가 추가 징집병이나 예비군을 모집할 여력이 안 된다거나 러시아 내에서 우크라이나 침공에 \n대한...",
        "link": "https://www.donga.com/news/Inter/article/all/20220308/112218766/1",
        "date": "1주 전",
        "image_path": "https://dimg.donga.com/a/600/0/90/5/wps/NEWS/IMAGE/2022/03/08/112218731.2.jpg",
        "catagory": "교전 최신 상황"
    },
    {
        "name": "우크라이나 사태: 러시아 침공 11일째 상황",
        "description": "현지 주민들은 수도 근처 지역인 부차, 호스토멜, 이르핀에서 러시아군과 격렬한 전투가 벌어졌으며 포격이 쉴 새 없이 쏟아졌다고 말했다. \n민간인들이...",
        "link": "https://www.bbc.com/korean/news-60643146",
        "date": "1주 전",
        "image_path": "https://ichef.bbci.co.uk/news/1024/branded_korean/1713/production/_123570950_hi074374380.jpg",
        "catagory": "교전 최신 상황"
    },
    {
        "name": "우크라이나: 키예프 거리 교전 시작...'무기를 내려놓지 않을 것'",
        "description": "TOP 뉴스. 1. 우크라이나 전쟁: 미 외신기자 피격 사망…러시아 침공 18일째 상황.",
        "link": "https://www.bbc.com/korean/international-60519286",
        "date": "3주 전",
        "image_path": "https://ichef.bbci.co.uk/news/1024/branded_korean/2D2A/production/_123426511_b1c622b5-f334-463a-ad74-d51e187a8601.jpg",
        "catagory": "교전 최신 상황"
    },
    {
        "name": "우크라 침공: '새로운 철의 장막이 쳐졌다'... 키예프 외곽 교전중",
        "description": "우크라이나의 수도 키예프 인근에서 24일(현지시간) 치열한 전투가 벌어진 가운데 우크라이나군은 러시아의 침공을 막아내기 위해 고군분투 \n중이다.",
        "link": "https://www.bbc.com/korean/60518994",
        "date": "3주 전",
        "image_path": "https://ichef.bbci.co.uk/news/1024/branded_korean/15F9B/production/_123411009_hi074103583.jpg",
        "catagory": "교전 최신 상황"
    },
    {
        "name": "푸틴, '핵전력 특별 전투 체제' 명령...우크라이나 \"평화협상 개시 합의\"",
        "description": "이런 가운데, 우크라이나 측은 벨라루스 국경에서 러시아와 대화하겠다고 밝혔습니다. 푸틴 대통령은 27일 러시아의 핵전력을 \"특별 \n전투임무 체제\"에...",
        "link": "https://www.voakorea.com/a/6461924.html",
        "date": "2주 전",
        "image_path": "https://gdb.voanews.com/01bd0000-0aff-0242-cf3e-08d9fa1281e6_w1200_r1.jpg",
        "catagory": "교전 최신 상황"
    },
    {
        "name": "“우크라이나 전쟁 현장을 게임 방송하듯 생방송”···MBC, 유튜브 생중계 논란",
        "description": "MBC가 자사 유튜브 채널에서 러시아군이 침공해 교전 중인 우크라이나 수도 ... 우크라이나 침공' 현지 상황 실시간 영상'이라는 \n제목으로 방송되고...",
        "link": "https://m.khan.co.kr/national/national-general/article/202202281551001",
        "date": "2주 전",
        "image_path": "https://img.khan.co.kr/news/2022/02/28/2022022801003422900310282.jpg",
        "catagory": "교전 최신 상황"
    },
    {
        "name": "러-우크라 전쟁 게임체인저 'TB2'드론이 궁금하다",
        "description": "바이락타르 TB2(Bayraktar TB2)로 불리는 이 전투드론은 우크라이나 방어 ... 올린 동영상은 총 5개로 러시아에 대한 드론 \n공격 상황을 잘 보여준다.",
        "link": "https://www.tech42.co.kr/%EB%9F%AC-%EC%9A%B0%ED%81%AC%EB%9D%BC-%EC%A0%84%EC%9F%81-%EA%B2%8C%EC%9E%84%EC%B2%B4%EC%9D%B8%EC%A0%80-tb2%EB%93%9C%EB%A1%A0%EC%9D%B4-%EA%B6%81%EA%B8%88%ED%95%98%EB%8B%A4/",
        "date": "13시간 전",
        "image_path": "https://www.tech42.co.kr/wp-content/uploads/2022/03/2▲터키군이-주로-사용하는-전투드론인-바이락타르-TB2.-사진위키피디아.jpg",
        "catagory": "교전 최신 상황"
    },
    {
        "name": "영국 특수부대 출신까지 우크라이나로…외국인들, 전장으로 ...",
        "description": "또 영국 최정예 공수특전단 SAS 출신들이 우크라이나로 향했다는 소식도 전해졌다. 현지 매체 미러는 40~60세 사이 SAS 예비역들이 \n교전 상황에서...",
        "link": "https://www.mk.co.kr/news/world/view/2022/03/199306/",
        "date": "2주 전",
        "image_path": "https://file.mk.co.kr/meet/neds/2022/03/image_readtop_2022_199306_16462763794963368.jpg",
        "catagory": "교전 최신 상황"
    },
    {
        "name": "\"전쟁터 우크라이나 시설에 남겨진 아동 10만명 이상\"",
        "description": "우크라이나에 발이 묶인 수백만 명에 달하는 아동은 국가전의 교전사태를 피해 ... 세이브더칠드런은 우크라이나의 전쟁이 격화되는 상황에서 \n피난을...",
        "link": "https://www.mk.co.kr/news/world/view/2022/03/242451/",
        "date": "1일 전",
        "image_path": "https://file.mk.co.kr/meet/neds/2022/03/image_readtop_2022_242451_16474109684976914.jpg",
        "catagory": "교전 최신 상황"
    }
]