[
    {
        "name": "러시아군, 오데사 등 우크라이나 남부 집중 공격",
        "description": "군 당국은 하르키우 인근 도시인 이줌에서 가장 격렬한 전투가 벌어지고 있다며 우크라이나 공군이 러시아 폭격기 한 대를 격추시키고 \n조종사를 체포...",
        "link": "https://www.hani.co.kr/arti/international/international_general/1037385.html",
        "date": "17시간 전",
        "image_path": "https://flexible.img.hani.co.kr/flexible/normal/730/486/imgdb/original/2022/0404/20220404500962.jpg",
        "catagory": "교전 최신 상황"
    },
    {
        "name": "“적들에게 죽음을” 우크라 여성들, 전투 투입 자원 - 조선일보",
        "description": "러시아의 우크라이나 침공 사태가 열흘 넘게 지속되고 있다. 우크라이나 현지에서는 자신의 도시와 고향을 지키려는 주민들의 저항이 이어지고 \n있다.",
        "link": "https://www.chosun.com/international/international_general/2022/03/08/BQQUW64AI5E6TCF24PDQGMTKAA/",
        "date": "4주 전",
        "image_path": "https://images.chosun.com/resizer/WyXWx5l9pPcRveaSXasTuLp0PgE=/718x376/smart/cloudfront-ap-northeast-1.images.arcpublishing.com/chosun/SQ6CQVA4LVEGHMRDKVD5Q5TSTE.png",
        "catagory": "교전 최신 상황"
    },
    {
        "name": "푸틴 “우크라이나 전투에 추가 징집병 안 보낸다”",
        "description": "이런 상황에서 푸틴 대통령의 공식 발언은 러시아가 추가 징집병이나 예비군을 모집할 여력이 안 된다거나 러시아 내에서 우크라이나 침공에 \n대한...",
        "link": "https://www.donga.com/news/Inter/article/all/20220308/112218766/1",
        "date": "4주 전",
        "image_path": "https://dimg.donga.com/a/600/0/90/5/wps/NEWS/IMAGE/2022/03/08/112218731.2.jpg",
        "catagory": "교전 최신 상황"
    },
    {
        "name": "“총으로 위협 후 성폭행”…속속 드러나는 '추악한 전쟁범죄'",
        "description": "교전 상황서 보호 엄두 못 내. “사회 전반 깊은 고통 초래”. 우크라이나의 러시아군 점령 지역에서 전시 강간 피해 사례들이 보고되는 \n등 광범위한...",
        "link": "https://www.khan.co.kr/world/europe-russia/article/202204042139005",
        "date": "5시간 전",
        "image_path": "https://img.khan.co.kr/spko/company/Khan_CI_180212.jpg",
        "catagory": "교전 최신 상황"
    },
    {
        "name": "우크라이나 사태: 러시아 침공 11일째 상황",
        "description": "현지 주민들은 수도 근처 지역인 부차, 호스토멜, 이르핀에서 러시아군과 격렬한 전투가 벌어졌으며 포격이 쉴 새 없이 쏟아졌다고 말했다. \n민간인들이...",
        "link": "https://www.bbc.com/korean/news-60643146",
        "date": "1개월 전",
        "image_path": "https://ichef.bbci.co.uk/news/1024/branded_korean/1713/production/_123570950_hi074374380.jpg",
        "catagory": "교전 최신 상황"
    },
    {
        "name": "\"푸틴, 동부 장악 후 5월 9일 승리 선언\"...美, 우크라 탱크 지원",
        "description": "BBC, 워싱턴포스트(WP) 등에 따르면 러시아군은 격렬한 전투 끝에 지난 1일 동부의 전략적 요충지인 이지움을 장악했다. 볼로디미르 \n젤렌스키 우크라이나...",
        "link": "https://news.koreadaily.com/2022/04/03/society/international/20220403013100343.html",
        "date": "2일 전",
        "image_path": "https://news.koreadaily.com/data/photo/2022/04/03/95412ec2-e59c-4d6d-a16b-8f28b8afd943.jpg",
        "catagory": "교전 최신 상황"
    },
    {
        "name": "정부, 우크라이나에 의약품·전투식량 등 군수물자 지원",
        "description": "정부는 러시아 침공에 맞서 싸우고 있는 우크라이나에 전투식량, 의약품, 방탄헬멧 등 무기가 아닌 군수물자를 지원하기로 결정했다.",
        "link": "https://www.hani.co.kr/arti/politics/defense/1034894.html",
        "date": "3주 전",
        "image_path": "https://flexible.img.hani.co.kr/flexible/normal/970/647/imgdb/original/2022/0315/20220315501867.jpg",
        "catagory": "교전 최신 상황"
    },
    {
        "name": "[이해영 칼럼] 서방 언론은 허구였다!, 러시아 뜻대로 끝나가는 전쟁",
        "description": "전투중 우크라이나군 총 260,200명 중 사상자 3만명, ... 지금까지의 협상상황과 앞서 말한 전황을 교차대조해 보면 교전이 가일층 \n격렬해 지는 이유...",
        "link": "https://firenzedt.com/21536",
        "date": "4시간 전",
        "image_path": "https://cdn.firenzedt.com/wp-content/uploads/2022/04/shutterstock_2039898137-scaled-e1649077586186.jpg",
        "catagory": "교전 최신 상황"
    },
    {
        "name": "“러시아군 3주 만에 7000명 사망”…사기 저하가 전투에 영향 줄까",
        "description": "우크라이나 전쟁에서 러시아 병력 손실이 커지면서 군 사기 저하가 러시아의 문제가 됐다는 분석이 나왔다. 미 정보당국은 지난달 24일 \n우크라이나 침공...",
        "link": "https://www.hani.co.kr/arti/international/international_general/1035227.html",
        "date": "2주 전",
        "image_path": "https://flexible.img.hani.co.kr/flexible/normal/640/427/imgdb/original/2022/0317/20220317502344.jpg",
        "catagory": "교전 최신 상황"
    },
    {
        "name": "“전투에 참가하겠다”…우크라이나로 돌아가는 여성들",
        "description": "16일 폴란드 남동부 프셰미실 중앙역의 5번 승강장. 지난달 24일 러시아의 우크라이나 침공 후 두 딸을 데리고 고국을 떠났던 \n우크라이나 여성 타티...",
        "link": "https://www.donga.com/news/Inter/article/all/20220317/112386256/1",
        "date": "2주 전",
        "image_path": "https://dimg.donga.com/a/600/0/90/5/wps/NEWS/IMAGE/2022/03/17/112384932.6.jpg",
        "catagory": "교전 최신 상황"
    },
    {
        "name": "\"러시아 지금 전투 불능 상태\"…미국 자신 있게 말한 이유 [러, 우크라 침공]",
        "description": "지난달 24일(현지시간) 우크라이나를 침공한 러시아군의 사망자가 7000명에 이르는 것으로 나타났다 미국 정보당국을 인용해 \n뉴욕타임스(NYT)가 17일...",
        "link": "https://www.mk.co.kr/news/world/view/2022/03/248734/",
        "date": "2주 전",
        "image_path": "https://file.mk.co.kr/meet/neds/2022/03/image_readtop_2022_248734_16475596384978947.jpg",
        "catagory": "교전 최신 상황"
    },
    {
        "name": "[우크라 침공] \"집단학살은 진군지체 때마다 나온 '푸틴 교과서'\"",
        "description": "대신 러시아군은 곳곳에서 우크라이나군과 치열한 교전을 이어가며 민간 ... 안에 남겨진 주민들은 외부 보급로가 막힌 상황에서 밖으로 \n빠져나가지...",
        "link": "https://www.mk.co.kr/news/world/view/2022/04/300480/",
        "date": "17시간 전",
        "image_path": "https://file.mk.co.kr/meet/yonhap/2022/04/04/image_readtop_2022_300480_0_111211.jpg",
        "catagory": "교전 최신 상황"
    },
    {
        "name": "“전투식량 유효기간 20년 넘어”… 우크라전으로 드러난 러軍 실태 - 조선일보",
        "description": "우크라이나를 침공하자마자 곧바로 수도 키이우(키예프)를 점령할 것이라 예상했던 러시아군이 2주째 고전하면서, 러시아 군대의 허점이 \n드러났다.",
        "link": "https://www.chosun.com/international/international_general/2022/03/09/ZQE4KNEYL5D5PMECDOPIXLKPGU/",
        "date": "4주 전",
        "image_path": "https://images.chosun.com/resizer/JwD4VdSIQWcf-s61LvTMKqGvmRE=/1200x630/smart/cloudfront-ap-northeast-1.images.arcpublishing.com/chosun/XZ2PG5TUQFEWBAM7I2NKM3N47M.JPG",
        "catagory": "교전 최신 상황"
    },
    {
        "name": "우크라이나 전쟁: 미 외신기자 피격 사망…러시아 침공 18일째 상황",
        "description": "러시아 침공 18일째 상황. 2022년 3월 14일. 우크라이나 서부 야보리우의 군사 훈련 기지가 러시아군 순항 미사일의 집중 공격. \n사진 출처, Reuters. 사진 설명,.",
        "link": "https://www.bbc.com/korean/news-60732812",
        "date": "3주 전",
        "image_path": "https://ichef.bbci.co.uk/news/1024/branded_korean/1557/production/_123636450_e7392a40-2933-401f-af6e-fead99e8db39.jpg",
        "catagory": "교전 최신 상황"
    },
    {
        "name": "우크라이나 분단으로 가나...\"푸틴, 한국 시나리오 생각해\"",
        "description": "우크라이나의 영토 보존 여부는 향후 러시아군과 우크라이나군의 교전 상황, 평화협상 추이, 러시아 점령지역 주민들의 태도 등 여러 \n복합적인 변수에...",
        "link": "https://m.khan.co.kr/world/europe-russia/article/202203281716021",
        "date": "1주 전",
        "image_path": "https://img.khan.co.kr/news/2022/03/28/2022032801003629600322941.jpg",
        "catagory": "교전 최신 상황"
    },
    {
        "name": "[우크라 침공] 러시아, 돈바스에 화력 집중하는 이유는",
        "description": "NYT에 따르면 우크라이나는 친러 분리주의 반군과 러시아군과의 전투를 위해 돈바스에 전체 군대의 3분의 1 이상을 배치한 것으로 \n추정된다. 러시아군이...",
        "link": "https://www.mk.co.kr/news/world/view/2022/03/290686/",
        "date": "4일 전",
        "image_path": "https://file.mk.co.kr/meet/yonhap/2022/03/31/image_readtop_2022_290686_0_144111.jpg",
        "catagory": "교전 최신 상황"
    },
    {
        "name": "\"우리는 최전방에서 전투할 것\" 우크라이나 도착한 이근 대위가 외교부 경고에도 전투를 강행한다는 입장을 밝혔다",
        "description": "의용군 참전을 위해 우크라이나로 출국한 이근 대위가 외교부 경고에 “우리는 최전방에서 전투 할 것”이라고 전투 강행 입장을 보였다.",
        "link": "https://m.huffingtonpost.kr/entry/ukraine-lee-geun_kr_6225ae67e4b012a2628cf2ff",
        "date": "1개월 전",
        "image_path": "https://img.huffingtonpost.com/asset/6225b8602300005f32136cf1.png?cache=4oYuxvRY5l&ops=1200_630",
        "catagory": "교전 최신 상황"
    },
    {
        "name": "젤렌스키 \"러시아군 격퇴중, 승리 확신\"...푸틴에 정상회담 제안",
        "description": "젤렌스키 대통령은 러시아의 침공 17일째인 이날 수도 크이우(러시아명 키예프)에서 외신 기자회견을 열어 이같이 밝히고, 우크라이나군이 \n주요 전투...",
        "link": "https://www.voakorea.com/a/6482204.html",
        "date": "3주 전",
        "image_path": "https://gdb.voanews.com/01C7F6D0-4768-401C-87B6-BEA3E7C1E9A7_w1200_r1.jpg",
        "catagory": "교전 최신 상황"
    },
    {
        "name": "러軍 통화 감청했더니…\"전투식량 질려, 개 잡아먹었다\"",
        "description": "[이데일리 이선영 기자] 러시아의 우크라이나 침공이 1개월 이상 지속되고 있는 가운데 부실한 전투식량에 질린 러시아군 병사가 개를 \n잡아먹었다는...",
        "link": "https://www.edaily.co.kr/news/read?newsId=01403846632291856&mediaCodeNo=257",
        "date": "3일 전",
        "image_path": "https://image.edaily.co.kr/images/Photo/files/NP/S/2022/04/PS22040100164.jpg",
        "catagory": "교전 최신 상황"
    },
    {
        "name": "자존심까지 걸린 마리우폴…러-우 “결코 포기 못한다”",
        "description": "우크라이나 정부가 21일(현지시각) 남동부 주요 교전지인 마리우폴에서 군 ... 마리우폴을 둘러싼 전투는 우크라이나군과 러시아군의 \n'자존심'과 명분...",
        "link": "https://www.hani.co.kr/arti/international/international_general/1035767.html",
        "date": "2주 전",
        "image_path": "https://flexible.img.hani.co.kr/flexible/normal/730/443/imgdb/original/2022/0322/20220322501491.jpg",
        "catagory": "교전 최신 상황"
    },
    {
        "name": "러, 주요 도시 장악실패…우크라 각지 교전상황은?[우크라전쟁 ...",
        "description": "우크라이나군은 이날 키이우 교외 마카리브에서 러시아군을 몰아내고 통제권을 되찾았다고 주장했다. 크림반도-돈바스 잇는 마리우폴…포위는 \n성공·점령은...",
        "link": "https://www.edaily.co.kr/news/read?newsId=04116406632266272&mediaCodeNo=257",
        "date": "2주 전",
        "image_path": "https://image.edaily.co.kr/images/Photo/files/NP/S/2022/03/PS22032301594.jpg",
        "catagory": "교전 최신 상황"
    },
    {
        "name": "20년 지난 전투식량 배급… 제트기엔 구식 무기 장착 - 조선일보",
        "description": "러시아군은 미국과 함께 세계 최고 전력이라는 평가를 받았지만 우크라이나에서는 지상군이 아직 수도 키이우(키예프)에 진입하지 못했고, \n공군 제트기들...",
        "link": "https://www.chosun.com/international/international_general/2022/03/10/AFGV3PVZ2RFTNGSFTCCW4B7UYI/",
        "date": "3주 전",
        "image_path": "https://images.chosun.com/resizer/82I7rR-YjSQcFGh4_2HTqBqzQV8=/700x367/smart/cloudfront-ap-northeast-1.images.arcpublishing.com/chosun/52IAKPBGRFAXFGFDA76TXHHKEE.jpg",
        "catagory": "교전 최신 상황"
    },
    {
        "name": "러시아-우크라이나 전쟁: 최근 전개 상황 < 전쟁/난민 < 국제 ...",
        "description": "볼로디미르 젤렌스키 우크라이나 대통령은 9일(현지시간) 12시간의 휴전 동안 우크라이나 교전 지역에서 최소 35,000명의 민간인이 \n대피했다고 밝혔다...",
        "link": "https://www.gukjenews.com/news/articleView.html?idxno=2423456",
        "date": "3주 전",
        "image_path": "https://cdn.gukjenews.com/news/thumbnail/202203/2423456_2416932_1423_v150.jpg",
        "catagory": "교전 최신 상황"
    },
    {
        "name": "푸틴 발 핵공포, '검은 목요일' 만드나 [정인설의 워싱턴나우]",
        "description": "우크라이나의 상황은 일시적 휴전, 불안한 휴전, 말로만 휴전입니다. ... 우크라이나군이 안전을 염려해 원전 주변에서 교전을 포기했기 \n때문에...",
        "link": "https://www.hankyung.com/finance/article/202203077883i",
        "date": "1개월 전",
        "image_path": "https://img.hankyung.com/photo/202203/01.29187329.1.jpg",
        "catagory": "교전 최신 상황"
    },
    {
        "name": "‘인도적’ 차원의 비행금지 설정… 美가 우크라 요청 거부하는 이유 - 조선일보",
        "description": "우크라이나 조종사 중에 폴란드로 와서 그걸 몰고갈 잉여 자원이 있는지, 폴란드 미그기의 현 상황이 전투에 적합한지, 우크라이나에 \n미그기를 분해-조립...",
        "link": "https://www.chosun.com/international/europe/2022/03/17/K6RSKJ233VG2XI3GZPM3DFUOB4/",
        "date": "2주 전",
        "image_path": "https://images.chosun.com/resizer/P9PKbmgLhZF8YPcKaJabt2BW0-A=/1200x630/smart/cloudfront-ap-northeast-1.images.arcpublishing.com/chosun/N46ZHTU4LVMZBF2MZ3NCGN447M.jpg",
        "catagory": "교전 최신 상황"
    },
    {
        "name": "우크라이나군, 키이우 등에서 반격 '성과'…전쟁 장기화",
        "description": "이날 키이우 동부의 전투에서는 우크라이나군이 러시아군을 외곽으로 20㎞ 이상 후퇴시키는 데 성공했다고 방송은 전했다. 미 국방부 \n관계자는 전날 키...",
        "link": "https://www.hani.co.kr/arti/international/international_general/1036068.html",
        "date": "1주 전",
        "image_path": "https://flexible.img.hani.co.kr/flexible/normal/730/456/imgdb/original/2022/0324/20220324501278.jpg",
        "catagory": "교전 최신 상황"
    },
    {
        "name": "우크라 침공 한달 러 “돈바스에만 집중”... 美 “종전전략 찾는 듯” - 조선일보",
        "description": "러시아의 우크라이나 전면 침공이 교착 국면으로 빠져든 가운데, ... 특히 돈바스 상황과 관련해서 “동부 도네츠크와 루한스크 지역에서 \n러시아군의...",
        "link": "https://www.chosun.com/international/2022/03/27/RYEHH3O3RVCFZESM7V3V3VY7U4/",
        "date": "1주 전",
        "image_path": "https://images.chosun.com/resizer/CNODzBuAcs7sdUXsW9uzbw74kZQ=/1200x630/smart/cloudfront-ap-northeast-1.images.arcpublishing.com/chosun/662K7LL5LJISDBHCD7Z2GYZBF4.jpg",
        "catagory": "교전 최신 상황"
    },
    {
        "name": "러의 키이우 진입로 2곳 차단당해… 시신 2500구 한밤중 극비 송환도 - 조선일보",
        "description": "이런 상황에서 러시아가 우크라이나에서 사망한 자국군 시신 2500여 구를 심야 ... 공습에 이어 지상군 교전까지 본격화하면서 상황이 \n악화되고 있다.",
        "link": "https://www.chosun.com/international/2022/03/20/7EHHHRYQHFBSFCIXP3ODF4F7YA/",
        "date": "2주 전",
        "image_path": "https://images.chosun.com/resizer/7hOhPPlBUuAhUktIGGGSTDSWyRA=/1200x630/smart/cloudfront-ap-northeast-1.images.arcpublishing.com/chosun/T6Z2UEH4N5PCJO5HNDN66PEW4A.jpg",
        "catagory": "교전 최신 상황"
    },
    {
        "name": "미 전쟁연구소 “우크라-러 전쟁, 교착 상태로 가는 중”",
        "description": "우크라이나 전쟁이 교착상태로 향하고 있으며, 러시아는 이를 타개하기 위해 ... 파스샹달 전투를 예로 들면서, 전쟁에서 교착상태는 \n양쪽이 상황을...",
        "link": "https://www.hani.co.kr/arti/international/international_general/1035584.html",
        "date": "2주 전",
        "image_path": "https://flexible.img.hani.co.kr/flexible/normal/640/427/imgdb/original/2022/0321/20220321500182.jpg",
        "catagory": "교전 최신 상황"
    },
    {
        "name": "우크라 전쟁 중 최고의 투자처는 러시아 루블화?! [정인설의 워싱턴나우]",
        "description": "우크라이나 전쟁도 그렇고 내 주식에서도 강한 회복 탄력성을 기대해봅니다. 러시아는 6주 간의 전투에서 바닥 난 병력과 장비를 다시 \n채워넣고 있습니다.",
        "link": "https://www.hankyung.com/finance/article/202204039245i",
        "date": "1일 전",
        "image_path": "https://img.hankyung.com/photo/202204/01.29502531.1.jpg",
        "catagory": "교전 최신 상황"
    }
]