[
    {
        "name": "[톺뉴스] 틱톡으로 들여다보는 우크라이나 전쟁",
        "description": "(서울=연합뉴스) 러시아의 전격적인 침공으로 시작된 우크라이나 전쟁이 열흘 ... 틱톡으로 들여다보는 우크라이나의 실시간 상황과 전쟁을 \n반대하는...",
        "link": "https://www.yna.co.kr/view/MYH20220304016700797",
        "date": "2주 전",
        "image_path": "https://img4.yna.co.kr/mpic/YH/2022/03/04/MYH20220304016700797.jpg",
        "catagory": "지역 라이브 상황"
    },
    {
        "name": "[우크라 침공] 우크라, 미국에 장기전 대비한 자금지원 요청",
        "description": "미국은 우크라이나에 지원하는 무기는 공격용이 아닌 방어용이며 우크라이나에 실시간 정보를 제공하지만 치명적인 목표물에 대한 정보는 \n제공하지...",
        "link": "https://www.mk.co.kr/news/world/view/2022/03/251266/",
        "date": "1일 전",
        "image_path": "https://file.mk.co.kr/meet/yonhap/2022/03/18/image_readtop_2022_251266_0_163311.jpg",
        "catagory": "지역 라이브 상황"
    },
    {
        "name": "비트코인 軍자금, 머스크 스타링크… 이런 전쟁은 없었다 - 조선일보",
        "description": "지난 24일 러시아군이 우크라이나로 침공하는 과정은 물론 우크라이나 내 움직임까지 구글맵에 실시간으로 공개되고 있다. 새벽 시간대 \n러시아와...",
        "link": "https://www.chosun.com/economy/tech_it/2022/02/28/OWCUFP6TYFFE7OTHLTYQYDHSXE/",
        "date": "3주 전",
        "image_path": "https://images.chosun.com/resizer/t0uMTbtNqBkiGRxwcI_k4K-ZbzA=/1200x630/smart/cloudfront-ap-northeast-1.images.arcpublishing.com/chosun/5H3D3RROBNEJ5D6X5VBMDC3V4A.JPG",
        "catagory": "지역 라이브 상황"
    },
    {
        "name": "[곽재원의 4차 산업혁명] 우크라이나 사태와 '실시간 경제' 혁명",
        "description": "이런 상황에서 지금 가장 난감해하는 사람들은 세계경제의 현실을 진단하고 향후를 전망하려는 관측통(이코노미스트)들이다. 신종 코로나 \n바이러스의 팬...",
        "link": "https://www.etoday.co.kr/news/view/2111588",
        "date": "2주 전",
        "image_path": "https://img.etoday.co.kr/pto_db/2022/03/20220306181451_1725272_210_268.jpg",
        "catagory": "지역 라이브 상황"
    },
    {
        "name": "[권은경] 우크라이나를 돕는 세계의 손길",
        "description": "세계 가장 거대한 검색 사이트인 구글은 구글 지도에서 교통상황을 실시간 보여주는 기능을 우크라이나 내에서 차단해 러시아 군이 활용할 수 \n없게...",
        "link": "https://www.rfa.org/korean/commentary/ad8cc740acbd/kekcu-03182022103601.html",
        "date": "1일 전",
        "image_path": "https://www.rfa.org/korean/commentary/ad8cc740acbd/kekcu-03182022103601.html/@@images/image/social_media",
        "catagory": "지역 라이브 상황"
    },
    {
        "name": "'우크라가 민간인 공격'? 러시아의 주장이 틀린 이유",
        "description": "우크라이나 전역에 인터넷이 확충되어 있고, 대부분의 사람들이 스마트폰과 SNS를 사용한다. 그리고, 그들은 실시간으로 피해상황을 찍어서 \nSNS에...",
        "link": "http://www.ohmynews.com/NWS_Web/View/at_pg.aspx?CNTN_CD=A0002818659",
        "date": "2일 전",
        "image_path": "http://ojsfile.ohmynews.com/CRI_T_IMG/2022/0316/A0002818659_T.jpg",
        "catagory": "지역 라이브 상황"
    },
    {
        "name": "우크라 현장통신 “창문에서 떨어진 복도에 누워 폭발음을 듣고 ...",
        "description": "키예프·오데사 현지인이 <한겨레>에 알려온 전쟁 상황 ... “우크라이나 방송사들은 전쟁 상황을 실시간 보도할 뿐 아니라 국민이 공황 \n상태에 빠지지...",
        "link": "https://www.hani.co.kr/arti/society/society_general/1033046.html",
        "date": "2주 전",
        "image_path": "https://flexible.img.hani.co.kr/flexible/normal/970/648/imgdb/original/2022/0301/20220301502117.jpg",
        "catagory": "지역 라이브 상황"
    },
    {
        "name": "“전쟁 영상을 게임 보듯 소비”…MBC, 유튜브 생중계 논란",
        "description": "우크라이나·러시아 양국 대통령을 비난하는 글이나 우크라이나의 상황과 무관한 혐오성 댓글도 쉽게 볼 수 있다. 교전중인 상황 실시간 중계 \n시청자 댓글...",
        "link": "https://m.khan.co.kr/national/media/article/202202282220015",
        "date": "3주 전",
        "image_path": "https://img.khan.co.kr/news/2022/02/28/2022030101000026400317001.jpg",
        "catagory": "지역 라이브 상황"
    },
    {
        "name": "전사자 태운 차량… 우크라 시민들, 거리에 무릎 꿇고 예우했다 - 조선일보",
        "description": "13일(현지시각) 우크라이나 현지 상황을 실시간으로 전하는 페이스북 페이지에는 “우크라이나 크멜니츠키 지역에서 쓰러진 영웅을 맞이하는 \n모습”...",
        "link": "https://www.chosun.com/international/international_general/2022/03/14/S74OONMFKZEZZKJYSRYDA2D5JY/",
        "date": "5일 전",
        "image_path": "https://images.chosun.com/resizer/kpbPl9ANMJXI9RDC0KGgR70Njoo=/500x262/smart/cloudfront-ap-northeast-1.images.arcpublishing.com/chosun/DVIEA4GZGJHFHC43DMKS5WADR4.gif",
        "catagory": "지역 라이브 상황"
    },
    {
        "name": "20만 세계 해커의 반격… 러 외무부·은행 홈피 마비 - 조선일보",
        "description": "구글은 지도 서비스인 구글맵의 우크라이나 현지 도로 상황을 실시간으로 보여주는 기능을 일시적으로 차단했다. 러시아가 구글맵을 보고 \n우크라이나...",
        "link": "https://www.chosun.com/economy/tech_it/2022/03/02/CVN5QC2XQZEAJP65BJUPRBZ3BE/",
        "date": "2주 전",
        "image_path": "https://images.chosun.com/resizer/-WGG_gi1hC4vBpaHYJ4J2rVI374=/696x365/filters:focal(305x323:315x333)/cloudfront-ap-northeast-1.images.arcpublishing.com/chosun/S3AFLXIYNFHDHH6373VZPMKPVA.jpg",
        "catagory": "지역 라이브 상황"
    },
    {
        "name": "정부·산업계, 우크라이나 전쟁에 실물경제 악영향 우려 초긴장",
        "description": "산업부는 공급망 교란으로 원자재 및 에너지 수급 상황에 문제가 생길 가능성에 대비해 수급 상황을 실시간 점검하고 있다. 러시아나 \n우크라이나가...",
        "link": "https://www.hani.co.kr/arti/economy/economy_general/1032459.html",
        "date": "3주 전",
        "image_path": "https://flexible.img.hani.co.kr/flexible/normal/640/407/imgdb/original/2022/0224/20220224503354.jpg",
        "catagory": "지역 라이브 상황"
    },
    {
        "name": "산업부, 수출통제 상담창구 '러시아 데스크' 본격 가동",
        "description": "정부가 우크라이나 사태에 대비하기 위해 러시아 데스크를 본격 가동한다. ... 진출·수출기업의 상황을 실시간으로 모니터링하면서 지원 \n대책 마련에...",
        "link": "https://www.korea.kr/news/policyNewsView.do?newsId=148899315",
        "date": "3주 전",
        "image_path": "https://www.korea.kr/newsWeb/resources/attaches/2022.02/24/a57f5e3093e1cb3872988c6af8caa64f.jpg",
        "catagory": "지역 라이브 상황"
    },
    {
        "name": "산업부, '우크라 침공' 美제재 파장 최소화에 총력…무역안보반 ...",
        "description": "미국이 러시아의 우크라이나 침공을 규탄하면서 반도체 등 하이테크 제품의 ... 산업부는 25일 '실물경제대책본부' 산하에 실시간 상황 \n점검 및 수출...",
        "link": "http://mobile.busan.com/view/busan/view.php?code=2022022511543242569",
        "date": "3주 전",
        "image_path": "http://www.busan.com/nas/wcms/wcms_data/photos/2022/02/25/2022022511561944509_l.jpg",
        "catagory": "지역 라이브 상황"
    },
    {
        "name": "우크라이나 부총리, 한국 기업에 위성영상 제공 요청…업체 ...",
        "description": "페도로프 부총리는 “러시아군과 장비의 움직임을 야간에도 파악하기 위해 실시간으로 제공되는 고해상의 합성개구레이더(SAR) 위성영상이 \n필요하다”며...",
        "link": "https://m.dongascience.com/news.php?idx=52708",
        "date": "2주 전",
        "image_path": "https://image.dongascience.com/Photo/2022/03/16462870890774.JPG",
        "catagory": "지역 라이브 상황"
    },
    {
        "name": "‘MBC에 분노’ 우크라이나 모델 올레나, 기부 호소 “전쟁 지원이 께름칙하면...”",
        "description": "올레나는 러시아 공습을 받은 우크라이나 현지 상황을 실시간으로 공유하며 “한국에서도 알아야 한다”고 안타까운 마음을 드러내기도 했다.",
        "link": "https://www.mk.co.kr/news/world/view/2022/03/191423/",
        "date": "2주 전",
        "image_path": "https://file.mk.co.kr/meet/neds/2022/03/image_readtop_2022_191423_16461115664960981.png",
        "catagory": "지역 라이브 상황"
    },
    {
        "name": "우크라이나 시민들, 탱크 앞세운 러시아군에 소셜미디어로 맞서다",
        "description": "트위터와 페이스북, 틱톡 등 소셜미디어에 실시간으로 전쟁의 참상을 ... 탱크가 연료가 떨어져 오도 가도 못하게 된 상황을 비웃는 \n모습이 담겼고,...",
        "link": "https://www.hani.co.kr/arti/international/europe/1033181.html",
        "date": "2주 전",
        "image_path": "https://flexible.img.hani.co.kr/flexible/normal/553/369/imgdb/original/2022/0302/20220302502896.jpg",
        "catagory": "지역 라이브 상황"
    },
    {
        "name": "우크라이나 모델 올레나, 8억 기부 한국에 \"무한한 감사\"",
        "description": "올레나는 MBC 에브리원 예능 프로그램 '대한 외국인'에 출연한 모델로, 지난달 24일 러시아가 우크라이나를 침공하자 고향 우크라이나 \n현지 상황을 실시간...",
        "link": "https://www.mk.co.kr/star/hot-issues/view/2022/03/201267/",
        "date": "2주 전",
        "image_path": "https://file.mk.co.kr/meet/neds/2022/03/image_readtop_2022_201267_16462958584963843.jpg",
        "catagory": "지역 라이브 상황"
    },
    {
        "name": "'우크라 침공 규탄' 나선 애플, 러시아서 판매 중단",
        "description": "우크라이나 주민 안전을 위해 애플지도에서 현지 교통상황 및 실시간 사건을 알려주는 기능도 사용할 수 없게 했다. 애플은 “러시아의 \n우크라이나 침공에...",
        "link": "https://www.hani.co.kr/arti/international/international_general/1033187.html",
        "date": "2주 전",
        "image_path": "https://flexible.img.hani.co.kr/flexible/normal/640/415/imgdb/original/2022/0302/20220302503147.jpg",
        "catagory": "지역 라이브 상황"
    },
    {
        "name": "러-우크라이나 전쟁을 보는 우리의 자세는?",
        "description": "실시간으로 신문, 방송, SNS를 통해 전해지는 우크라이나 상황은 보고도 믿기지 않는다. 러시아 푸틴 대통령은 친러 반정부군이 장악하고 \n있는 우크라이나...",
        "link": "https://www.gunchinews.com/news/articleView.html?idxno=63144",
        "date": "5일 전",
        "image_path": "http://www.gunchinews.com/news/thumbnail/202203/63144_65754_935_v150.jpg",
        "catagory": "지역 라이브 상황"
    },
    {
        "name": "“평생 라켓만 잡았지만 나도 총 들겠다” 우크라이나 테니스 스타도 예비군 합류 - 조선일보",
        "description": "지금 예비군 등록 신청자가 계속 몰려들고 있는 상황”이라고 전했다. 우크라이나는 크림반도부터 수도 키예프 부근까지 러시아로부터 전방위 \n침공을...",
        "link": "https://www.chosun.com/sports/sports_general/2022/02/26/D2YV4D2BVZEPDL3QYMHPGUIPZQ/",
        "date": "3주 전",
        "image_path": "https://images.chosun.com/resizer/szD7x_T2uv4-IFijTKbXCmLfcDo=/400x210/smart/cloudfront-ap-northeast-1.images.arcpublishing.com/chosun/623Z5TNU4ZGB7NNR4TU3NAMNOU.jpg",
        "catagory": "지역 라이브 상황"
    }
]