[
    {
        "name": "계속되는 4차 회담…러 “진전”vs우크라 “제자리” - 조선일보",
        "description": "우크라이나 사태를 두고 러시아와 우크라이나 정부가 4차 평화협상을 이어가고 있는 협상 진행 상황에 대한 양측의 평가가 엇갈린다.",
        "link": "https://www.chosun.com/international/international_general/2022/03/19/GJU6HO6SSBCZNGXHOEPBJAJOXI/",
        "date": "1개월 전",
        "image_path": "https://images.chosun.com/resizer/m6nb3Yw58InbJ1XWK6z_1LnOTTY=/1200x630/filters:focal(666x416:676x426)/cloudfront-ap-northeast-1.images.arcpublishing.com/chosun/U5CCILCANRHUJJQ2BE3R7O43FM.jpg",
        "catagory": "협상 진행 과정"
    },
    {
        "name": "[우크라 침공] 4차 평화협상 러 “진전”·우크라 “제자리걸음” - 미주 ...",
        "description": "그는 \"우크라이나의 탈나치화와 탈군사화 등과 같은 주제들에 대한 협상 진전 상황은 다양하게 평가할 수 있다\"면서 \"탈군사화 문제는 \n(진전이) 50%...",
        "link": "http://www.koreatimes.com/article/20220318/1407146",
        "date": "1개월 전",
        "image_path": "http://image.koreatimes.com/photos/LosAngeles/tag_img.jpg",
        "catagory": "협상 진행 과정"
    },
    {
        "name": "러 \"중립국화·나토 불가입 의견 접근\"... 우크라 \"아니다\"",
        "description": "러시아 협상단을 이끄는 블라디미르 메딘스키 대통령실 보좌관은 18일(현지시간) 기자들에게 협상 상황을 설명하며 \"우크라이나의 중립국화 \n및 나토...",
        "link": "http://www.ohmynews.com/NWS_Web/View/at_pg.aspx?CNTN_CD=A0002819290",
        "date": "1개월 전",
        "image_path": "http://ojsfile.ohmynews.com/CT_T_IMG/2022/0319/IE002958714_LT.jpg",
        "catagory": "협상 진행 과정"
    },
    {
        "name": "러시아군 \"마리우폴 함락\"‥우크라이나 항복 요구하며 최후통첩",
        "description": "우크라이나 측은 저항 중인 자국군을 건드리면 러시아와의 협상은 중단될 ... 볼로디미르 젤렌스키 우크리이나 대통령은 마리우폴의 상황이 \n심각...",
        "link": "https://imnews.imbc.com/replay/2022/nwdesk/article/6360106_35744.html",
        "date": "7시간 전",
        "image_path": "https://image.imnews.imbc.com/replay/2022/nwdesk/article/__icsFiles/afieldfile/2022/04/17/desk_20220417_201018_1_8_Large.jpg",
        "catagory": "협상 진행 과정"
    },
    {
        "name": "우크라 끝까지 지킨다…러 '생명유지 시한' 무시한 마지막 방어군",
        "description": "마리우폴을 수비하고 있는 우크라이나 방어군이 러시아측의 최후통첩을 ... 볼로디미르 젤렌스키 우크라이나 대통령은 러시아의 행위에 \n'평화협상...",
        "link": "https://news.koreadaily.com/2022/04/17/society/international/20220417064235356.html",
        "date": "20시간 전",
        "image_path": "https://news.koreadaily.com/data/photo/2022/04/17/f05d8e75-5634-467a-acf2-2cc102ae32d3.jpg",
        "catagory": "협상 진행 과정"
    },
    {
        "name": "[우크라이나 침공] 러 “마리우폴 거의 점령” vs. 젤렌스키 “우리군 ...",
        "description": "젤렌스키 대통령은 “우리 군이 버티고 있지만, 상황이 위급하다”면서 “러시아가 마리우폴에서 저항 중인 우크라이나 군을 전멸시킨다면 \n협상은 중단될...",
        "link": "https://www.etoday.co.kr/news/view/2124604",
        "date": "16시간 전",
        "image_path": "https://img.etoday.co.kr/pto_db/2022/04/600/20220417103524_1740931_1199_799.jpg",
        "catagory": "협상 진행 과정"
    },
    {
        "name": "[유로 스코프] 우크라이나 중립화 해법 ‘동상이몽’… 전쟁의 출구가 안 보인다 - 조선일보",
        "description": "러시아는 우크라이나가 버틸 수 있는 한계를 느낄 때까지 잔혹하고 강한 위협을 계속하며 더 유리한 조건에서 협상을 하려 한다.",
        "link": "https://www.chosun.com/opinion/specialist_column/2022/04/18/QHBBTDWVLBFGTJN77AQ32UZ6BQ/",
        "date": "33분 전",
        "image_path": "https://images.chosun.com/resizer/4WwOUjpgNEHhuWpRAH0G93ZH2n8=/1200x630/smart/cloudfront-ap-northeast-1.images.arcpublishing.com/chosun/JPUI74VPOJAJNN2I7P4LM42LBU.jpg",
        "catagory": "협상 진행 과정"
    },
    {
        "name": "우크라·미국·영국 안보보좌관 삼각논의…'평화협상' 초점",
        "description": "예르마크 보좌관은 \"우리는 평화협상 상황과 전망을 논의했다. 핵심 사안은 우크라이나 국가안보를 보장하는 국제 체제\"라고 말했다. \n우크라는 나토 가입...",
        "link": "https://www.fnnews.com/news/202204151918430863",
        "date": "2일 전",
        "image_path": "https://image.fnnews.com/resource/media/image/2022/04/15/202204151926242848_l.jpg",
        "catagory": "협상 진행 과정"
    },
    {
        "name": "마리우폴 함락 위기....러시아 \"극초음속 무기 우크라이나 타격\"",
        "description": "러시아군이 우크라이나 침공 24일째인 19일, 남동부 항구도시 마리우폴 ... 한편, 정전협상 진행 상황을 두고 러시아와 우크라이나에서 \n각각 다른...",
        "link": "https://www.voakorea.com/a/6492559.html",
        "date": "1개월 전",
        "image_path": "https://gdb.voanews.com/995ca37d-2012-4825-8048-01f28e1dad08_w1200_r1.jpg",
        "catagory": "협상 진행 과정"
    },
    {
        "name": "전쟁으로 10조 잃은 우크라 재벌 \"종전 후 재건 도울 것\"",
        "description": "러시아가 최후통첩을 보낸 상황으로, 러시아군에 따르면 우크라이나군은 ... 은 마리우폴에서 저항 중인 우크라이나군을 사살한다면 \n러시아와의 협상...",
        "link": "https://www.mk.co.kr/news/world/view/2022/04/341508/",
        "date": "14시간 전",
        "image_path": "https://file.mk.co.kr/meet/neds/2022/04/image_readtop_2022_341508_16501683045012086.jpg",
        "catagory": "협상 진행 과정"
    },
    {
        "name": "이탈리아 총리 \"'침공말라' 마지막까지 푸틴 설득했지만…\"",
        "description": "아울러 전쟁이 터진 이후 다시 이뤄진 푸틴 대통령과의 통화에서 전쟁 종식을 위해 볼로디미르 젤렌스키 우크라이나 대통령과 만나 협상해야 \n한다고...",
        "link": "https://www.mk.co.kr/news/world/view/2022/04/342597/",
        "date": "4시간 전",
        "image_path": "https://file.mk.co.kr/meet/yonhap/2022/04/17/image_readtop_2022_342597_0_231411.jpg",
        "catagory": "협상 진행 과정"
    },
    {
        "name": "\"푸틴 숨은 의도는 우크라이나 초토화…항복 아니면 협상 않을 것\"",
        "description": "러시아의 우크라이나 침공이 한 달째 이어지는 가운데 블라디미르 푸틴 러시아 대통령은 우크라이나가 사실상 항복하는 상황이 되지 않는 한 \n협상에...",
        "link": "https://www.pressian.com/pages/articles/2022032317105512736",
        "date": "3주 전",
        "image_path": "https://www.pressian.com/_resources/10/2022/03/23/2022032209342865670_l.jpg",
        "catagory": "협상 진행 과정"
    },
    {
        "name": "푸틴, “평화협상 막다른 골목에 이르러…계속 싸우겠다”",
        "description": "이에 대해 우크라이나도 러시아와의 평화협상이 “극도로 어려운 상황”이라고 밝혔다. 미하일로 포돌랴크 우크라이나 대통령실 보좌관은 이날 \n서면 논평을...",
        "link": "https://www.hani.co.kr/arti/international/europe/1038674.html",
        "date": "4일 전",
        "image_path": "https://flexible.img.hani.co.kr/flexible/normal/545/336/imgdb/original/2022/0413/20220413500175.jpg",
        "catagory": "협상 진행 과정"
    },
    {
        "name": "우크라이나, 마리우폴 공격 계속 평화협상 중단 '레드라인' 경고",
        "description": "AP 통신과 CNN 등에 따르면 쿨레바 외무장관은 이날 CBS 방송 '페이스 더 네이션'과 회견에서 러시아군의 포위 공세로 함락 위기에 \n몰린 마리우폴의 상황...",
        "link": "https://www.fnnews.com/news/202204180237003709",
        "date": "59분 전",
        "image_path": "https://image.fnnews.com/resource/media/image/2022/04/18/202204180236479745_l.jpg",
        "catagory": "협상 진행 과정"
    },
    {
        "name": "[우크라 침공] 전선 교착속 협상진척 상황은…영토문제 최대난관",
        "description": "전쟁이 장기화할 우려가 제기되는 상황에서도 더 이상의 참화를 막기 위한 협상은 절박하게 진행되는 형국이다. 볼로디미르 젤렌스키 \n우크라이나 대통령은...",
        "link": "https://m.mk.co.kr/news/world/view/2022/03/257001/",
        "date": "4주 전",
        "image_path": "https://file.mk.co.kr/meet/yonhap/2022/03/21/image_readtop_2022_257001_0_154712.jpg",
        "catagory": "협상 진행 과정"
    },
    {
        "name": "우크라 5차 협상 진전…러 “키이우서 군사활동 줄이겠다”",
        "description": "우크라이나 협상단의 다비드 아라하미야 집권당 대표는 “오늘 협상 결과 ... 대통령 보좌관은 협상 뒤 기자회견에서 “협상이 건설적으로 \n진행됐다”며...",
        "link": "https://www.hani.co.kr/arti/international/international_general/1036755.html",
        "date": "3주 전",
        "image_path": "https://flexible.img.hani.co.kr/flexible/normal/970/647/imgdb/original/2022/0330/4116485680361079.jpg",
        "catagory": "협상 진행 과정"
    },
    {
        "name": "러 외무 \"우크라, 이스탄불 협상 합의 번복…새 협정안 제안\"",
        "description": "인테르팍스 통신 등에 따르면 라브로프 장관은 이날 자국 기자들에게 평화 협상 진행 상황에 관해 설명하며 \"어제 우크라이나가 지난달 \n이스탄불 회담...",
        "link": "https://www.mk.co.kr/news/world/view/2022/04/315595/",
        "date": "1주 전",
        "image_path": "https://file.mk.co.kr/meet/yonhap/2022/04/07/image_readtop_2022_315595_0_231611.jpg",
        "catagory": "협상 진행 과정"
    },
    {
        "name": "[우크라 침공] 우크라 \"러시아와 평화협상 극도로 어려워\"",
        "description": "우크라이나가 러시아와의 평화 협상이 \"극도로 어려운 상황\"이라는 입장을 밝혔다. AFP 통신에 따르면 미하일로 포돌랴크 우크라이나 \n대통령실 보좌관...",
        "link": "https://www.mk.co.kr/news/world/view/2022/04/329167/",
        "date": "5일 전",
        "image_path": "https://file.mk.co.kr/meet/yonhap/2022/04/13/image_readtop_2022_329167_0_085411.jpg",
        "catagory": "협상 진행 과정"
    },
    {
        "name": "러시아·우크라이나 평화협상 난항 - TBS",
        "description": "우크라이나에서의 특별 군사작전에 대해서는 \"러시아의 작전은 계획에 따라 진행되고 있으며 모든 초기 목표가 달성되면 결론을 내릴 \n것\"이라면서 \"예정...",
        "link": "https://tbs.seoul.kr/news/newsView.do?typ_800=4&idx_800=3467010&seq_800=20459649",
        "date": "4일 전",
        "image_path": "http://58.234.158.21:8081/Upload/Image/20220413/00000000000001284974.jpg",
        "catagory": "협상 진행 과정"
    },
    {
        "name": "“협상, 극히 어려워” 러-우크라 평화협상 난항",
        "description": "우크라이나도 러시아와의 평화 협상이 어려운 상황이라고 밝혔다. 미하일로 포돌랴크 우크라이나 대통령 ... 협상은 “계속 진행 중이다”고 \n덧붙였다.",
        "link": "https://www.donga.com/news/Inter/article/all/20220413/112850110/1",
        "date": "4일 전",
        "image_path": "https://dimg.donga.com/a/600/0/90/5/wps/NEWS/IMAGE/2022/04/13/112850102.2.jpg",
        "catagory": "협상 진행 과정"
    },
    {
        "name": "부차 학살…우크라이나 전쟁 장기화로 가는 '변곡점' 되나",
        "description": "분노한 볼로디미르 젤렌스키 대통령은 6일 유엔 안전보장이사회에서 “이런 상황에서 어떻게 평화협상을 하느냐”고 말했다. 조 바이든 미국 \n대통령 역시...",
        "link": "https://www.hani.co.kr/arti/international/international_general/1038001.html",
        "date": "1주 전",
        "image_path": "https://flexible.img.hani.co.kr/flexible/normal/970/646/imgdb/original/2022/0407/20220407503277.jpg",
        "catagory": "협상 진행 과정"
    },
    {
        "name": "[朝鮮칼럼 The Column] 한국은 왜 우크라이나를 지지해야 하는가",
        "description": "러시아의 우크라이나 침공에 대해 문재인 정부의 초기 반응은 미지근했다. ... 전쟁이 아닌 대화와 협상으로 해결되어야 한다”며 \n소극적으로 말했다.",
        "link": "https://www.chosun.com/opinion/chosun_column/2022/04/16/TXLXXWXRZBG2XP3M4VE27GLK2E/",
        "date": "2일 전",
        "image_path": "https://images.chosun.com/resizer/5zW1TphcsYZN_uzN4ICi4LPpqjw=/1200x630/smart/cloudfront-ap-northeast-1.images.arcpublishing.com/chosun/UAFBROEW35NDTOF74HG3IYQEGA.jpg",
        "catagory": "협상 진행 과정"
    },
    {
        "name": "우크라 “키이우 수도권 탈환” 선언… 동·남부 최대 격전지 예고",
        "description": "러시아군이 돈바스 지역을 모두 점령하기 위해 우크라이나와의 평화협상 진행 상황을 지켜보며 화력을 쏟아 부을 것으로 관측되고 있다.",
        "link": "https://m.hankookilbo.com/News/Read/A2022040311430002626",
        "date": "2주 전",
        "image_path": "https://newsimg-hams.hankookilbo.com/2022/04/03/7329d00a-4462-417c-9534-862b225819d1.jpg?t=20220417183528",
        "catagory": "협상 진행 과정"
    },
    {
        "name": "[특파원 리포트] 우크라이나 부총리가 말하는 정전협상…“국민의 ...",
        "description": "정전협상 상황은? ... 러시아-우크라이나 정전 협상 어디까지 진행? ... 우크라이나는 절대적 군사력이 러시아에 못 미치는 상황에서 \n이를 받아들이면...",
        "link": "https://news.kbs.co.kr/news/view.do?ncd=5421124",
        "date": "4주 전",
        "image_path": "http://news.kbs.co.kr/data/fckeditor/new/image/2022/03/22/290361647927175053.jpg",
        "catagory": "협상 진행 과정"
    },
    {
        "name": "“첼시 구단주, 푸틴 직접 승인하에 우크라와 협상 추진” FT",
        "description": "블라디미르 푸틴 러시아 대통령이 우크라이나와 휴전 협상에 러시아 ... 협상 진행 상황을 보고받은 서방 당국자들은 아브라모비치가 실제로 \n협상과...",
        "link": "https://www.donga.com/news/Inter/article/all/20220325/112538487/1",
        "date": "3주 전",
        "image_path": "https://dimg.donga.com/a/600/0/90/5/wps/NEWS/IMAGE/2022/03/25/112538377.2.jpg",
        "catagory": "협상 진행 과정"
    },
    {
        "name": "[속보]우크라이나 러시아, 전쟁 평화 협상 극도로 어려운 상황?",
        "description": "우크라이나가 러시아와의 평화 협상이 \"극도로 어려운 상황\"이라는 입장을 밝혔다. AFP 통신에 따르면 미하일로 포돌랴크 우크라이나 \n대통령실 보좌관...",
        "link": "https://www.jeonmae.co.kr/news/articleView.html?idxno=883635",
        "date": "4일 전",
        "image_path": "https://www.jeonmae.co.kr/news/thumbnail/202204/883635_575838_98_v150.jpg",
        "catagory": "협상 진행 과정"
    },
    {
        "name": "마크롱 \"우-러 합의 가능성 낮아\"",
        "description": "러시아 국영RIA통신에 따르면 크렘린궁은 \"통화에서 두 정상은 러시아와 우크라이나 간 진행 중인 협상 내용을 포함해 우크라이나 상황과 \n관련한 의견...",
        "link": "https://m.hankookilbo.com/News/Read/A2022032308300004865?rPrev=A2022032311160001088",
        "date": "3주 전",
        "image_path": "https://newsimg-hams.hankookilbo.com/2022/03/23/ceb5b9c1-d4df-4096-88b6-c662943e4c7a.jpg?t=20220417183534",
        "catagory": "협상 진행 과정"
    },
    {
        "name": "'러시아 흔적 지운다' 키이우 랜드마크, 개명 작업 돌입",
        "description": "그러면서 우크라이나군이 현재 물과 식량 없이 절망적 상황에 처해있다고 주장했다. ... 반박하며 자국군을 없애면 협상을 중단할 것이라고 \n경고했다.",
        "link": "https://cm.asiae.co.kr/article/2022041719560931636",
        "date": "8시간 전",
        "image_path": "https://cphoto.asiae.co.kr/listimglink/6/2022041719544832162_1650192889.jpeg",
        "catagory": "협상 진행 과정"
    },
    {
        "name": "러·우 평화협상 진전…바이든 “말이 아닌 행동으로 파단하겠다”",
        "description": "우크라이나는 안보 보장을 전재로 중립국화 요구를 받아들일 수 있다고 밝혔고, 러시아는 “협상이 건설적으로 진행됐다”며 신뢰 강화 \n차원에서...",
        "link": "https://m.khan.co.kr/world/world-general/article/202203300829001",
        "date": "2주 전",
        "image_path": "https://img.khan.co.kr/news/2022/03/30/2022033001003930800350561.jpg",
        "catagory": "협상 진행 과정"
    },
    {
        "name": "러시아, 우크라이나, 터키서 5차 평화협상 개최",
        "description": "다만, 협상 개시일에 대해서는 양측의 발표가 엇갈리는 상황이다. 로이터 통신에 따르면 우크라이나 측 협상 대표단 구성원인 다비드 \n하라하미야 집권당...",
        "link": "https://www.radiokorea.com/news/article.php?uid=384685",
        "date": "3주 전",
        "image_path": "",
        "catagory": "협상 진행 과정"
    }
]