[
    {
        "name": "미국, 총기규제 논란 가열/NY Times 사설 “우크라이나, 현실 ...",
        "description": "미국, 총기규제 논란 가열/NY Times 사설 “우크라이나, 현실 직시하라” 강력 비판. 주형석 기자 입력 05.26.2022 \n08:50 AM 수정 05.26.2022 09:15 AM 조회 1,069.",
        "link": "https://radiokorea.com/news/article.php?uid=388908",
        "date": "2일 전",
        "image_path": "https://rk-img-news.s3.us-west-2.amazonaws.com/2022/05/26/388908/1.jpg",
        "catagory": "규제"
    },
    {
        "name": "\"일본, 방위장비 수출 규제 완화 검토…전투기 등도 대상\"",
        "description": "지난 3월 일본 정부는 러시아의 침공을 받은 우크라이나에 방위 물자를 제공하기 위해 방위장비 이전 3원칙의 운용지침을 일부 개정해 \n방탄복과 헬멧...",
        "link": "https://www.mk.co.kr/news/world/view/2022/05/471799/",
        "date": "17시간 전",
        "image_path": "https://file.mk.co.kr/meet/yonhap/2022/05/28/image_readtop_2022_471799_0_102411.jpg",
        "catagory": "규제"
    },
    {
        "name": "마리우폴 부상병 200여명 구조...미국, 쿠바 송금∙여행 규제 완화",
        "description": "진행자) 오늘은 어떤 소식들이 있습니까? 기자) 네. 우크라이나 남부 마리우폴 제철소에서 저항하던 우크라이나 군인들의 대피가 \n진행됐습니다.",
        "link": "https://www.voakorea.com/a/6576891.html",
        "date": "1주 전",
        "image_path": "https://gdb.voanews.com/bb6e5a93-bf5b-4fca-95b9-bfc6931f8c23_w1200_r1.jpg",
        "catagory": "규제"
    },
    {
        "name": "트럼프 \"우크라 도울 돈으로 안전한 학교나 만들어라\"",
        "description": "러시아의 우크라이나 침공 직후 블라디미르 푸틴 러시아 대통령에게 ... 다만 트럼프가 말하는 '안전한 학교 만들기'에서 정작 총기 규제 \n강화는 쏙...",
        "link": "https://www.msn.com/ko-kr/news/world/%ED%8A%B8%EB%9F%BC%ED%94%84-%EC%9A%B0%ED%81%AC%EB%9D%BC-%EB%8F%84%EC%9A%B8-%EB%8F%88%EC%9C%BC%EB%A1%9C-%EC%95%88%EC%A0%84%ED%95%9C-%ED%95%99%EA%B5%90%EB%82%98-%EB%A7%8C%EB%93%A4%EC%96%B4%EB%9D%BC/ar-AAXOv72",
        "date": "14시간 전",
        "image_path": "No Image",
        "catagory": "규제"
    },
    {
        "name": "‘우크라 2박3일 취재’ 제한 변경… 2주간 11개주 취재 가능",
        "description": "외교부가 26일 취재 목적의 우크라이나 방문에 관한 기존 방침을 변경했다. ... 체르니우치주 지역에만 취재가 가능하도록 규제한다”고 \n비판했다.",
        "link": "http://www.mediatoday.co.kr/news/articleView.html?idxno=304222",
        "date": "1일 전",
        "image_path": "https://cdn.mediatoday.co.kr/news/thumbnail/202205/304222_412546_2728_v150.jpg",
        "catagory": "규제"
    },
    {
        "name": "쇠퇴하는 세계화… 식량·비료 수출규제 47건으로 급증 - 조선일보",
        "description": "코로나 팬데믹으로 가속화된 탈(脫)세계화 흐름이 러시아의 우크라이나 침공 사태와 맞물리면서 식량·비료 등을 무기화하는 극단적 \n보호무역주의 경향이...",
        "link": "https://www.chosun.com/international/international_general/2022/05/05/5EKZYPMTBVABLJO2C2MX4HLBDQ/",
        "date": "3주 전",
        "image_path": "https://images.chosun.com/resizer/y2c9MBNvwXuYDk7kQ6OyXjlSmZ8=/1200x630/smart/cloudfront-ap-northeast-1.images.arcpublishing.com/chosun/TQYPIQCNSNMKLCPSD4NN5FLXAQ.jpg",
        "catagory": "규제"
    },
    {
        "name": "푸틴이 불붙인 식량 보호주의…기아·물가 고통 커지고 길어진다",
        "description": "러시아의 우크라이나 침공 여파로 국제 곡물 가격이 뛰면서 식량 불안이 커지자 농산물이나 육류 등 식품 수출 ... 밀에서 고기까지 수출 \n규제 확산…",
        "link": "https://www.mk.co.kr/news/world/view/2022/05/471593/",
        "date": "21시간 전",
        "image_path": "https://file.mk.co.kr/meet/yonhap/2022/05/28/image_readtop_2022_471593_0_054612.jpg",
        "catagory": "규제"
    },
    {
        "name": "러軍의 220㎞ 해상 봉쇄… 4억명 먹일 곡물 수출길 막아버렸다 - 조선일보",
        "description": "유럽의 빵 바구니'라 불리는 우크라이나의 곡물 수출이 차단되면서, ... 민간 선박의 자유로운 항행를 보장하고, 전함의 통과를 규제하는 \n협정이다.",
        "link": "https://www.chosun.com/international/europe/2022/05/25/6EJEIDNQUZAPNP364ZWLXX6UHY/",
        "date": "3일 전",
        "image_path": "https://images.chosun.com/resizer/emPwO8UiypkepEfCI-DKYjmnh6o=/1200x630/filters:focal(873x120:883x130)/cloudfront-ap-northeast-1.images.arcpublishing.com/chosun/QDF7YKFEQRDJBLP5E7CNA5TNHY.png",
        "catagory": "규제"
    },
    {
        "name": "[시론] 우크라 전쟁과 러시아 핵위협",
        "description": "러시아의 우크라이나 침략이 3개월을 넘어서고 있다. ... 이들은 “이런 상황이 계속될 경우 핵무기에 대한 규제조치가 사라질 수 \n있다”며 “이는 우리...",
        "link": "https://news.koreadaily.com/2022/05/24/society/opinion/20220524184957952.html",
        "date": "4일 전",
        "image_path": "https://news.koreadaily.com/resources/images/logo/sns-logo.png",
        "catagory": "규제"
    },
    {
        "name": "러시아-우크라이나 전장에 '치명적' 살인로봇 등장",
        "description": "러시아가 우크라이나 침공 전쟁에서 치명적인 자율무기를 사용 중인 것으로 ... 미국은 살상 로봇을 규제하되 무력 사용에 대한 적절한 \n수준의 인간...",
        "link": "http://m.g-enews.com/article/Global-Biz/2022/05/202205220639014484e8b8a793f7_1",
        "date": "6일 전",
        "image_path": "https://nimage.g-enews.com/phpwas/restmb_allidxmake.php?idx=5&simg=2022052210043406383e8b8a793f7210178127232.jpg",
        "catagory": "규제"
    },
    {
        "name": "러, 우크라 점령지 주민에 자국 여권 발급",
        "description": "러시아가 우크라이나 남동부 마리우폴 등 우크라이나 내 점령지 주민들에게 러시아 여권을 ... 민간은행, 국부펀드 등과 거래할 수 없도록 \n규제했다.",
        "link": "https://www.donga.com/news/Inter/article/all/20220527/113645719/1",
        "date": "2일 전",
        "image_path": "No Image",
        "catagory": "규제"
    },
    {
        "name": "\"中외교부 부부장, 방송규제당국 수장될듯…서방과 선전전\"",
        "description": "러위청 중국 외교부 부부장(차관·58)이 중국 방송 규제 당국인 광전총국 ... 이달에는 화상 연설을 통해 \"미국은 우크라이나의 \n희생으로 유럽을 통제...",
        "link": "https://www.mk.co.kr/news/world/view/2022/05/465021/",
        "date": "2일 전",
        "image_path": "https://file.mk.co.kr/meet/yonhap/2022/05/26/image_readtop_2022_465021_0_113412.jpg",
        "catagory": "규제"
    },
    {
        "name": "“경제 3중고, 규제개혁으로 극복해야” : 뉴스",
        "description": "그러면서 “지금은 경기 침체와 금융 불안정에 더해 우크라이나 사태 등 지정학적 위험까지 겹친 복합적인 위기 국면”이라며 “물가는 \n오르는데 성장이...",
        "link": "https://www.donga.com/news/Economy/article/all/20220527/113646297/1",
        "date": "2일 전",
        "image_path": "https://dimg.donga.com/a/600/0/90/5/wps/NEWS/IMAGE/2022/05/27/113648751.1.jpg",
        "catagory": "규제"
    },
    {
        "name": "더 중요해진 클라우드…러 공격 직전 우크라 디지털인프라 대피",
        "description": "유럽연합(EU)의 빅테크 규제에 대해 그는 \"오늘날은 디지털 기술이 일상 ... 나델라 CEO는 \"저희는 러시아의 공격이 시작됐을 때 \n우크라이나 정부와...",
        "link": "https://www.mk.co.kr/news/economy/view/2022/05/463021/",
        "date": "3일 전",
        "image_path": "https://file.mk.co.kr/news/facebook_mknews.jpg",
        "catagory": "규제"
    },
    {
        "name": "적십자, 우크라이나 투항병 전쟁포로 등록...상하이 버스 운행 22 ...",
        "description": "국제적십자위원회(ICRC)가 우크라이나 마리우폴의 아조우스탈 제철소에서 나온 우크라이나 ... 중국 상하이시의 방역 규제가 점점 풀리고 \n있다고요?",
        "link": "https://www.voakorea.com/a/6580587.html",
        "date": "1주 전",
        "image_path": "https://gdb.voanews.com/03180000-0aff-0242-a67d-08da39268c17_w1200_r1.jpg",
        "catagory": "규제"
    },
    {
        "name": "러시아 푸틴, 우크라에 공식 선전포고하면 발생할 일",
        "description": "현재까지 러시아 정부는 우크라이나에서 '특별 군사 작전'을 펼치고 있다고 ... 징집, 군 복무 등 여러 관련 법에 따라 규제되며, \n시민들의 생활,...",
        "link": "https://www.bbc.com/korean/international-61305855",
        "date": "3주 전",
        "image_path": "https://ichef.bbci.co.uk/news/1024/branded_korean/17ED0/production/_124600089_26a7a0a6-379e-49f8-8eda-de22638bdfb9.jpg",
        "catagory": "규제"
    },
    {
        "name": "자재 대란·과잉 규제에… 둔촌주공 재건축, 초유의 공사 중단 - 조선일보",
        "description": "건설사들은 조합과 2016년 10월 2조6700억원에 공사비 계약을 할 때보다 건설 원가가 30% 이상 올랐다고 주장한다. 실제로 \n러시아·우크라이나 전쟁으로...",
        "link": "https://www.chosun.com/economy/real_estate/2022/05/27/SRQQXS43HFEXVCUOKVX6YEWZTE/",
        "date": "2일 전",
        "image_path": "https://images.chosun.com/resizer/5qDxTl-wJm7UUMbW9TJU5vT_nZM=/1200x630/filters:focal(34x283:44x293)/cloudfront-ap-northeast-1.images.arcpublishing.com/chosun/ZCXUQM563BF2DJEQBQ2MHCBCJA.jpg",
        "catagory": "규제"
    },
    {
        "name": "인도 갑작스러운 밀수출 규제로 수출 물량 180만t 묶여",
        "description": "하지만 올해는 우크라이나 전쟁 등으로 글로벌 밀 가격이 오르면서 농민들이 정부 대신 민간 수출업자에 대거 밀을 내다 파는 상황이 \n발생했다.",
        "link": "https://www.mk.co.kr/news/world/view/2022/05/434180/",
        "date": "1주 전",
        "image_path": "https://file.mk.co.kr/meet/yonhap/2022/05/17/image_readtop_2022_434180_0_133111.jpg",
        "catagory": "규제"
    },
    {
        "name": "“한국이 우크라이나 꼴 난다” ...환구시보의 입이 거친 이유 - 조선일보",
        "description": "이미 강대해진 중국이 러시아가 우크라이나 다루듯 한국을 손 봐 줄 ... 미국은 현재 대중 경계심을 잔뜩 높이며 산업 기술 등 각종 \n규제를 강화하는...",
        "link": "https://www.chosun.com/opinion/column/2022/05/11/KZ7LHUSM7RF7HBUVJKJUHZDMGQ/",
        "date": "2주 전",
        "image_path": "https://images.chosun.com/resizer/zDB1PBBPIYp1HKfjQtVbimbMnhg=/600x315/smart/cloudfront-ap-northeast-1.images.arcpublishing.com/chosun/6PDTD7GAVI2FYNUDBTSIXJQ3Z4.jpg",
        "catagory": "규제"
    },
    {
        "name": "식량위기 속 'GMO 수입' 딜레마에 처한 세계",
        "description": "러시아-우크라이나 전쟁으로 인한 식량위기 상황에서, ... 선진국들도 식량·사료 수급에 어려움이 닥치자 GMO 농산물 및 사료 관련 \n규제를 완화했다.",
        "link": "http://www.ikpnews.net/news/articleView.html?idxno=47485",
        "date": "6일 전",
        "image_path": "http://www.ikpnews.net/news/photo/202205/47485_32941_825.jpg",
        "catagory": "규제"
    },
    {
        "name": "[러시아·우크라이나 전쟁 이슈 읽기] 러시아 경제, 전쟁·서방제재 최악 상황 벗어나",
        "description": "전쟁 전에 달러당 70루블대 중반이었던 환율이 두 달여 만에 제자리로 돌아온 것이다. 이는 러시아 중앙은행이 외화 인출 규제와 기준금리 \n인상, 자국...",
        "link": "https://www.mk.co.kr/news/economy/view/2022/04/380371/",
        "date": "1개월 전",
        "image_path": "https://file.mk.co.kr/meet/neds/2022/04/image_readtop_2022_380371_16511868635024970.jpg",
        "catagory": "규제"
    },
    {
        "name": "추경호 부총리 불필요·과도한 금융 규제 과감히 정리",
        "description": "그는 \"물가는 가파르게 오르고 경기는 오히려 둔화하는 양상 속 미국 금리인상이 급격하게 진행되고 우크라이나 사태 장기화로 \n국제유가·원자재 등 가격...",
        "link": "https://www.ajunews.com/view/20220527125158083",
        "date": "1일 전",
        "image_path": "https://image.ajunews.com/content/image/2022/05/27/20220527125459714131.jpg",
        "catagory": "규제"
    },
    {
        "name": "바이든 미 대통령 첫 방한...미 400억 달러 우크라이나 추가 지원 예산안 가결",
        "description": "미국 상원이 400억 달러 규모의 우크라이나 지원 법안을 가결했습니다. ... 진행자) 최근 탈레반 정권이 여성들의 복장을 더 엄격히 \n규제하고 나섰다...",
        "link": "https://www.voakorea.com/a/6582309.html",
        "date": "1주 전",
        "image_path": "https://gdb.voanews.com/03180000-0aff-0242-f63b-08da3a6a80ae_w1200_r1.jpeg",
        "catagory": "규제"
    },
    {
        "name": "규제 개혁·세제 합리화로 '역동적 경제' 만든다",
        "description": "러시아-우크라이나 사태 등을 통해 불거진 글로벌 자원수급 불확실성은 에너지 신산업 등을 창출해 선제적으로 대응한다. 에너지믹스를 \n합리적으로 조정...",
        "link": "https://www.korea.kr/news/policyNewsView.do?newsId=148902014",
        "date": "2일 전",
        "image_path": "https://www.korea.kr/newsWeb/resources/attaches/2022.05/26/87490a0ae968a376790ab7bdf184d113.jpg",
        "catagory": "규제"
    },
    {
        "name": "WSJ, 러 독립언론 메두자 조명…\"미디어 탄압 견디며 생존투쟁\"",
        "description": "우크라이나 침공을 '특수 군사작전'이라고 명명하는 러시아 정부의 규제에 따라 TV 방송과 소셜미디어에는 정부의 선전용 메시지만 유통되고 \n있고,...",
        "link": "https://m.mk.co.kr/news/world/view/2022/05/397445/",
        "date": "3주 전",
        "image_path": "https://file.mk.co.kr/meet/yonhap/2022/05/04/image_readtop_2022_397445_0_163211.jpg",
        "catagory": "규제"
    },
    {
        "name": "한국무협, 뉴욕서 대러시아 전략물자 수출규제 가이드라인 세미나",
        "description": "러시아와 우크라이나 전쟁이 장기화됨에 따라 수출규제가 당분간 지속될 것이란 전망도 나왔다. 이 팀장은 \"미 상무부 BIS(Burea \nof Industry and...",
        "link": "https://www.hankyung.com/international/article/202205129503i",
        "date": "2주 전",
        "image_path": "https://img.hankyung.com/photo/202205/01.29944181.1.png",
        "catagory": "규제"
    },
    {
        "name": "바이든, 우크라에 42조원 추가 지원…\"한국과 천연가스 협력\"",
        "description": "우크라이나 추가 지원안에는 무기를 비롯한 군사적 지원 200억 ... 제재를 피하려는 사람을 규제 대상에 추가해 강도 높은 사법 단속의 \n범위에 넣는...",
        "link": "https://www.mk.co.kr/news/world/view/2022/04/380296/",
        "date": "1개월 전",
        "image_path": "https://file.mk.co.kr/meet/neds/2022/04/image_readtop_2022_380296_16511813765026058.jpg",
        "catagory": "규제"
    },
    {
        "name": "총기단체 막강한 로비에 막혀… 美, 잇단 참사에도 규제입법 ...",
        "description": "볼로디미르 젤렌스키 우크라이나 대통령은 \"무고한 아이들이 살해된 것에 깊은 슬픔을 느낀다\"며 \"우크라이나 국민은 희생자들의 친지와 \n친구, 그리고...",
        "link": "http://www.dt.co.kr/contents.html?article_no=2022052602109919607005",
        "date": "2일 전",
        "image_path": "http://contents.dt.co.kr/images/202205/2022052602109919607005[1].jpg?var=3102",
        "catagory": "규제"
    },
    {
        "name": "이번엔 설탕…인도 수출 규제에 또 식품 가격 인상 우려",
        "description": "설탕뿐만 아니라 우크라이나 전쟁으로 인한 각국의 식량안보 조치가 강화되면서 식량 인플레이션에 대한 우려가 커지고 있다. 인도는 지난 \n13일 밀 수출을...",
        "link": "http://news.tf.co.kr/read/economy/1941153.htm",
        "date": "2일 전",
        "image_path": "http://img.tf.co.kr/article/home/2022/05/26/20221861653530289.jpg",
        "catagory": "규제"
    },
    {
        "name": "에너지값 치솟자…영국, 석유·가스기업에 초과이윤세 25% 부과",
        "description": "러시아의 우크라이나 침공으로 국제 에너지 가격이 크게 오르자 영국과 ... 영국 전기·가스시장 규제기관인 오프젬(OFGEM)은 \n에너지요금 상한선이...",
        "link": "https://www.hani.co.kr/arti/international/international_general/1044633.html",
        "date": "1일 전",
        "image_path": "https://flexible.img.hani.co.kr/flexible/normal/730/471/imgdb/original/2022/0527/20220527500491.jpg",
        "catagory": "규제"
    }
]