[
    {
        "name": "[우크라 전쟁] 우크라이나 후원, 현금이 아닌 크립토 급증하는 ...",
        "description": "러시아-우크라이나 전쟁이 점점 심화됨에 따라 암호화폐가 우크라이나에 기부하기 위한 수단으로 자리 잡고 있다. 이는 사람들이 암호화폐로 \n자선...",
        "link": "https://www.wikileaks-kr.org/news/articleView.html?idxno=123680",
        "date": "1일 전",
        "image_path": "http://www.wikileaks-kr.org/news/thumbnail/202203/123680_106651_5444_v150.jpg",
        "catagory": "후원"
    },
    {
        "name": "후원사이트 공유하고, SNS 인증샷 올리고 - 조선일보",
        "description": "서울 강남구에 사는 대학원생 이모(24)씨는 지난 1일 유엔난민기구(UNHCR)를 통해 우크라이나에 20만원을 후원했다. 이씨는 \n“처음에는 사태가 이렇게...",
        "link": "https://www.chosun.com/national/national_general/2022/03/03/QHA5PHFWTZATHFBGETWZDUNDSY/",
        "date": "3주 전",
        "image_path": "/pf/resources/images/meta_default.png?d=759",
        "catagory": "후원"
    },
    {
        "name": "기부, 역사공부, 암호화폐 후원…각양각색 우크라이나 연대",
        "description": "유엔난민기구에는 정기후원을 신청했다”며 “앞으로도 우크라이나에 대해 잘못 아는 일이 없도록 더 찾아보고 공부하려고 한다”고 말했다. \n러시아로부터...",
        "link": "https://www.hani.co.kr/arti/society/society_general/1033377.html",
        "date": "3주 전",
        "image_path": "https://flexible.img.hani.co.kr/flexible/normal/640/638/imgdb/original/2022/0303/20220303503042.jpg",
        "catagory": "후원"
    },
    {
        "name": "ROTC중앙회 ‘우크라이나 후원 모금운동’ 전개",
        "description": "대한민국ROTC중앙회는 러시아 침공에 맞서 결사항전 중인 우크라이나 국민들에게 희망을 주기 위해 '우크라이나 돕기 후원 모금운동'을 \n전개하고...",
        "link": "https://www.donga.com/news/Society/article/all/20220304/112163981/1",
        "date": "3주 전",
        "image_path": "https://dimg.donga.com/a/600/0/90/5/wps/NEWS/IMAGE/2022/03/04/112163383.3.jpg",
        "catagory": "후원"
    },
    {
        "name": "\"도와주세요\" 주한 우크라이나대사관 모금 시작하자 성금 쇄도",
        "description": "주한 우크라이나대사관 인도지원 계좌 개설 시민들 '십시일반' 송금 인증샷 남겨 대사관 \"어려운 시기 후원 감사해\" 인사. 주한 \n우크라이나대사관...",
        "link": "https://m.hankookilbo.com/News/Read/A2022030217310000172",
        "date": "3주 전",
        "image_path": "https://newsimg-hams.hankookilbo.com/2022/03/02/47ea609c-335f-47b4-be46-3238b2d39bd0.jpg?t=20220327123956",
        "catagory": "후원"
    },
    {
        "name": "\"우크라이나 돕겠다\" 게임 구매부터 암호화폐 기부까지···후원 형태도 '다양'",
        "description": "게임업체 “게임 수익 우크라 적십자로” 2014년 출시작 구매·인증 행렬 이어져 우크라에 코인 기부…K팝 팬들도 나서. 한 누리꾼이 \n게임 '디스 워 오브...",
        "link": "https://m.khan.co.kr/article/202203021600011",
        "date": "3주 전",
        "image_path": "https://img.khan.co.kr/news/2022/03/02/2022030201000314400021152.jpg",
        "catagory": "후원"
    },
    {
        "name": "한국자총 서울지부, '우크라이나 평화기금' 1000만원 전달",
        "description": "드미트로 포노마렌코 주한 우크라이나 대사는 이번 후원 성금 전달과 관련해 이일준 수석부회장, 김성덕 운영위원장, 최재숙 여성회장 등에게 \n“한국...",
        "link": "http://www.seniormaeil.com/news/articleView.html?idxno=34917",
        "date": "11시간 전",
        "image_path": "http://www.seniormaeil.com/news/thumbnail/202203/34917_50374_1955_v150.jpg",
        "catagory": "후원"
    },
    {
        "name": "“남일 같지 않다”…일반시민들도 우크라 돕기 나섰다…후원금·물품기부",
        "description": "직장인 30대 김모씨는 러시아의 우크라이나 침공으로 어린아이들이 사망했다는 기사를 보고 눈물이 났다. 우크라이나에 도움을 줄 수 있는 \n방법을...",
        "link": "https://www.donga.com/news/Society/article/all/20220302/112118044/1",
        "date": "3주 전",
        "image_path": "https://dimg.donga.com/a/560/0/90/5/wps/NEWS/IMAGE/2022/03/02/112117744.2.jpg",
        "catagory": "후원"
    },
    {
        "name": "맨유: 우크라이나 침공 러시아 항공사 후원 계약 해지",
        "description": "잉글랜드 프리미어리그(EPL) 맨체스터 유나이티드(맨유)가 러시아의 우크라이나 침공 사태와 관련해 러시아 항공사와의 후원 계약을 \n해지했다.",
        "link": "https://www.bbc.com/korean/international-60519283",
        "date": "1개월 전",
        "image_path": "https://ichef.bbci.co.uk/news/1024/branded_korean/BFEB/production/_123413194_manutd.jpg",
        "catagory": "후원"
    },
    {
        "name": "\"우크라이나를 향한 남가주 한인교회 성도들의 사랑에 감사 ...",
        "description": "월드쉐어 USA(대표 강태광 목사)가 후원하는 우크라이나 군종 목사인 키므치(Vasily Khimich) 소령이 남가주 교회와 성도 \n그리고 후원자들이 보낸...",
        "link": "https://kr.christianitydaily.com/articles/112565/20220322/%EC%9A%B0%ED%81%AC%EB%9D%BC%EC%9D%B4%EB%82%98%EC%97%90-%EB%B3%B4%EC%97%AC%EC%A4%80-%EB%82%A8%EA%B0%80%EC%A3%BC-%ED%95%9C%EC%9D%B8%EA%B5%90%ED%9A%8C%EC%99%80-%EC%84%B1%EB%8F%84%EB%93%A4%EC%9D%98-%EB%94%B0%EB%9C%BB%ED%95%9C-%EC%82%AC%EB%9E%91%EC%97%90-%EA%B0%90%EC%82%AC%EB%93%9C%EB%A6%BD%EB%8B%88%EB%8B%A4.htm",
        "date": "4일 전",
        "image_path": "https://kr.christianitydaily.com/data/images/full/124277/vasily-khimich.jpg",
        "catagory": "후원"
    },
    {
        "name": "1만 원에 게임이 500개… 우크라이나 '후원 번들' 주요작 살펴보기",
        "description": "우크라이나 '후원 번들' 주요작 살펴보기 ... 인디게임 플랫폼 itch.io가 우크라이나 지원을 위해 최소 10달러로 총 992개 \n품목을 구매할 수 있는...",
        "link": "https://www.thisisgame.com/webzine/news/nboard/4/?n=144623",
        "date": "2주 전",
        "image_path": "https://file.thisisgame.com/upload/nboard/news/2022/03/10/20220310162756_7035.png",
        "catagory": "후원"
    },
    {
        "name": "'부활' 구수환감독, 우크라이나판 쉰들러리스트 주인공 돕기 나서 \"100여명 탈출\" - 조선일보",
        "description": "우크라이나 후원 참여는 이태석 재단 홈페이지에서 가능하다. /nyc@osen.co.kr. [사진] 이태석 재단...",
        "link": "https://www.chosun.com/entertainments/entertain_photo/2022/03/22/RZHTU5J6QZB3CK3SIZSGBWHG3I/",
        "date": "5일 전",
        "image_path": "https://images.chosun.com/resizer/fgiaLuirFaHbBkUWE6bOoH3tPVE=/550x288/smart/cloudfront-ap-northeast-1.images.arcpublishing.com/chosun/JFWA5K3JYVRZKUSEATA2GZHQAA.jpg",
        "catagory": "후원"
    },
    {
        "name": "우크라이나 국경 인근 난민센터에 직접 가 보니…",
        "description": "독자 여러분들의 기도와 후원 부탁드립니다. -편집자 주 ... 급히 1천 유로 분량의 식품을 사서 우크라이나 현지 교회에 보내 달라는 \n요청이었습니다.",
        "link": "https://www.christiantoday.co.kr/news/346484",
        "date": "1일 전",
        "image_path": "https://images.christiantoday.co.kr/data/images/full/345191/image.jpg",
        "catagory": "후원"
    },
    {
        "name": "[우크라이나 침공] 서방 대러 제재 전방위로 확대…현대차는 ...",
        "description": "[우크라이나 침공] 서방 대러 제재 전방위로 확대…현대차는 첼시 후원 중단. 입력 2022-03-13 16:51. 고대영 기자 \n구독하기. 제보하기.",
        "link": "https://www.etoday.co.kr/news/view/2113564",
        "date": "2주 전",
        "image_path": "https://img.etoday.co.kr/pto_db/2022/03/600/20220313164254_1727586_1200_755.jpg",
        "catagory": "후원"
    },
    {
        "name": "[단독] 이영애, 우크라 1억 후원 막전막후..\"러시아에 희생된 아이들 사진에 충격\"(종합) - 조선일보",
        "description": "[OSEN=박소영 기자] 배우 이영애가 러시아의 침공으로 아비규환이 된 우크라이나를 위로하기 위해 1억 원을 기부했다.",
        "link": "https://www.chosun.com/entertainments/entertain_photo/2022/03/01/RHLBU3SICSSNKCEQM67CCH4DRM/",
        "date": "4주 전",
        "image_path": "https://images.chosun.com/resizer/9Hy9u4KuvM-UJsLpCm7VGvCkxkM=/650x341/smart/cloudfront-ap-northeast-1.images.arcpublishing.com/chosun/E3VPNEQ7T4ATE3NTSETAV5C4ME.jpg",
        "catagory": "후원"
    },
    {
        "name": "러시아의 침공 후 급박했던 사흘간의 전황… NFT로 담아 전쟁 기금 마련하는 우크라 - 서울경제",
        "description": "애초에 우크라이나는 전 세계 시민들에게 후원금을 암호화폐로 받고 후원을 한 이들을 에어드롭(특정 토큰을 구입하면 이에 따라 보상 행위로 \n지급...",
        "link": "https://www.sedaily.com/NewsView/263KX097FH/GF01",
        "date": "9시간 전",
        "image_path": "https://newsimg.sedaily.com/2022/03/27/263KX097FH_1.jpg",
        "catagory": "후원"
    },
    {
        "name": "“70년 전 한국도…이제 우리가 우크라이나 어린이를 도울 때”",
        "description": "대한적십자사도 누리집에서 우크라이나 지원을 위한 모금을 진행하고 있다. 일시후원은 긴급지원에, 정기후원은 국제긴급구호기금으로 편입돼 \n분쟁,...",
        "link": "https://www.hani.co.kr/arti/society/society_general/1032886.html",
        "date": "4주 전",
        "image_path": "https://flexible.img.hani.co.kr/flexible/normal/645/429/imgdb/original/2022/0228/20220228502484.jpg",
        "catagory": "후원"
    },
    {
        "name": "[우크라 침공] 국내 구호단체·대학가 후원 봇물…\"도움 필요할 때\"",
        "description": "2일 재난 구호모금 전문기관인 희망브리지 전국재해구호협회에 따르면 이 단체는 전날부터 이달 31일까지 우크라이나 국민과 현지에 머무는 \n교민을 위한...",
        "link": "https://www.mk.co.kr/news/society/view/2022/03/196359/",
        "date": "3주 전",
        "image_path": "https://file.mk.co.kr/meet/yonhap/2022/03/02/image_readtop_2022_196359_0_174911.jpg",
        "catagory": "후원"
    },
    {
        "name": "침신대, 우크라이나와 산불피해 지역에 성금 전달",
        "description": "한국침례신학대학교(김선배 총장)는 지난 21일 러시아의 침공으로 고통받고 있는 우크라이나와 경북 울진과 강원도 산불피해 구호 후원금 \n7백만 원을...",
        "link": "https://www.christiandaily.co.kr/news/113777",
        "date": "4일 전",
        "image_path": "https://images.christiandaily.co.kr/data/images/full/91426/image.jpg",
        "catagory": "후원"
    },
    {
        "name": "우크라이나 200억 규모 암호화폐 기부금 받았다…일부는 NFT 판매금 후원 - 서울경제",
        "description": "우크라이나 정부가 1000만 달러(120억원)가 넘는 비트코인 기부를 받은 것으로 알려졌다. 일부는 대체 불가 코인을 판매한 자금으로 \n후원이 이뤄졌다.",
        "link": "https://www.sedaily.com/NewsVIew/262BE9LKAZ",
        "date": "4주 전",
        "image_path": "https://newsimg.sedaily.com/2022/02/28/262BE9LKAZ_1.jpg",
        "catagory": "후원"
    },
    {
        "name": "전쟁 피해 우크라이나 전방위 지원",
        "description": "기아대책은 우크라이나 난민을 돕기 위한 전용 후원 페이지를 개설하고 긴급 구호 모금을 진행하고 있다. 모인 금액은 우크라이나 현지인을 \n위한 긴급...",
        "link": "https://www.kidok.com/news/articleView.html?idxno=214842",
        "date": "1주 전",
        "image_path": "http://www.kidok.com/news/thumbnail/202203/214842_64909_356_v150.jpg",
        "catagory": "후원"
    },
    {
        "name": "세계 골프계, 우크라이나 후원에 연대 - 헤럴드경제 뉴스",
        "description": "세계 골프계, 우크라이나 후원에 연대 ... 팀=남화영 기자] 세계 골프계가 러시아의 우크라이나 침공을 반대하고 우크라이나와 연대에 \n동참하고 있다.",
        "link": "http://mbiz.heraldcorp.com/sports/view.php?ud=202203100555074543739_1",
        "date": "2주 전",
        "image_path": "//res.heraldm.com/phpwas/restmb_allidxmake.php?idx=5&simg=202203100555074543739_20220310055609_01.jpg",
        "catagory": "후원"
    },
    {
        "name": "우크라이나 눈물 닦아주자…시민들이 나섰다",
        "description": "또 우크라이나 국민 향한 도움의 손길도 이어지고 있다. 주한 우크라이나대사관이 SNS에 올린 우크라이나 국립은행 특별 후원 계좌 설립 \n소식. 페이스북...",
        "link": "https://www.kukinews.com/newsView/kuk202203020131",
        "date": "3주 전",
        "image_path": "http://www.kukinews.com/data/kuk/image/2022/03/02/kuk202203020246.jpg",
        "catagory": "후원"
    },
    {
        "name": "'푸틴 집회' 참석한 러시아 수영스타, 후원 파기당해",
        "description": "러시아는 2014년 군사 공격으로 우크라이나 영토인 크림반도를 강제 병합했다. 우크라이나는 이를 국제법 위반으로 규정하며 인정하지 않고 \n있다. close...",
        "link": "http://www.ohmynews.com/NWS_Web/View/at_pg.aspx?CNTN_CD=A0002820275",
        "date": "4일 전",
        "image_path": "http://ojsfile.ohmynews.com/CRI_T_IMG/2022/0323/A0002820275_T.jpg",
        "catagory": "후원"
    },
    {
        "name": "[우크라 침공] 이혜리·김윤아·엄지원…우크라이나 아동 위한 기부 잇따라",
        "description": "이제까지 40만 달러(약 4억8천만원)를 우크라이나 아동 등에 지원한 세이브더칠드런 코리아는 대중 모금 캠페인이 시작된 지 약 2주 \n만에 후원금 5...",
        "link": "https://www.mk.co.kr/news/society/view/2022/03/255642/",
        "date": "6일 전",
        "image_path": "https://file.mk.co.kr/meet/yonhap/2022/03/21/image_readtop_2022_255642_0_114712.jpg",
        "catagory": "후원"
    },
    {
        "name": "[단독] \"우크라이나를 위해\"…기부 빙자 '피싱' 주의보",
        "description": "하지만 유엔난민기구 한국지부 관계자는 \"해당 링크는 우리 기구 URL이 아니다\"라고 선을 그었다. 유엔난민기구 우크라이나 긴급 구호 \n활동 후원은 유엔...",
        "link": "https://m.inews24.com/v/1461341",
        "date": "1주 전",
        "image_path": "https://img-lb.inews24.com/v1/facebookexternalhit/face/626x352/05056b8c4e0466.jpg",
        "catagory": "후원"
    },
    {
        "name": "우크라이나 지원 모금 운동 이어져 < 교회와 세상 < 기사본문",
        "description": "러시아의 우크라이나 침공 8일째인 3일 우크라이나에 대한 인도적 지원을 ... 후원 계좌는 우리은행 1005-303-232450 \n(사)고통받는교회돕기한국지부,...",
        "link": "http://www.catholicnews.co.kr/news/articleView.html?idxno=32252",
        "date": "3주 전",
        "image_path": "http://cdn.catholicnews.co.kr/news/thumbnail/202203/32252_53060_936_v150.jpg",
        "catagory": "후원"
    },
    {
        "name": "“작은 마음이지만” 우크라 기부 인증 봇물…성금 8억 돌파[e글e글]",
        "description": "기부자들은 주한 우크라이나 대사관 공식 소셜미디어에 인증 글을 ... 기부자들은 후원 방법을 소개한 대사관 공식 페이스북 게시물을 통해 \n기부를...",
        "link": "https://www.donga.com/news/Society/article/all/20220303/112142299/2",
        "date": "3주 전",
        "image_path": "https://dimg.donga.com/a/600/0/90/5/wps/NEWS/IMAGE/2022/03/03/112142616.2.jpg",
        "catagory": "후원"
    },
    {
        "name": "뉴시스",
        "description": "[서울=뉴시스] 김제이 기자 = 러시아의 폭격으로 피해를 받은 우크라이나를 위한 후원의 물결이 크립토 커뮤니티에도 퍼져나갔다.",
        "link": "https://mobile.newsis.com/view.html?ar_id=NISX20220304_0001782378",
        "date": "3주 전",
        "image_path": "https://image.newsis.com/2022/03/04/NISI20220304_0018551132_web.jpg",
        "catagory": "후원"
    },
    {
        "name": "우크라이나 기부 행렬에 'SNS 활약상' 눈길…'가짜 모금'도 주의해야",
        "description": "지난 27일(현지시간) 우크라이나 외교부는 \"우크라이나 국립은행이 우크라이나군 지원을 위한 특별 후원 계좌를 개설했다\"고 발표했다.",
        "link": "https://www.news1.kr/articles/?4599976",
        "date": "4주 전",
        "image_path": "https://image.news1.kr/system/photos/2022/2/28/5243448/article.jpg",
        "catagory": "후원"
    }
]